requirements/__init__.py
requirements/requirements/__init__.py
requirements/requirements/analyzer.py
requirements/requirements/cli.py
requirements/requirements/mapping.py
reqdev-0.1.3.dist-info/METADATA
reqdev-0.1.3.dist-info/WHEEL
reqdev-0.1.3.dist-info/entry_points.txt
reqdev-0.1.3.dist-info/top_level.txt
reqdev-0.1.3.dist-info/RECORD
