Metadata-Version: 2.4
Name: reqdev
Version: 0.1.3
Summary: Smartly generates requirements.txt for Python projects with no virtual environment
Author: Naman Garg
Author-email: Naman Garg <namangarg2075@gmail.com>
License: MIT
Project-URL: Homepage, https://github.com/namangarg2075/reqdev
Project-URL: Bug Tracker, https://github.com/namangarg2075/reqdev/issues
Project-URL: Documentation, https://github.com/namangarg2075/reqdev#readme
Project-URL: Source Code, https://github.com/namangarg2075/reqdev
Keywords: requirements,dependencies,packaging,pip,dev-tools,requirements.txt,python
Classifier: Development Status :: 3 - Alpha
Classifier: Intended Audience :: Developers
Classifier: Programming Language :: Python :: 3
Classifier: Programming Language :: Python :: 3.7
Classifier: Programming Language :: Python :: 3.8
Classifier: Programming Language :: Python :: 3.9
Classifier: Programming Language :: Python :: 3.10
Classifier: Programming Language :: Python :: 3.11
Classifier: Programming Language :: Python :: 3.12
Classifier: Topic :: Software Development :: Libraries :: Python Modules
Classifier: Topic :: Software Development :: Build Tools
Classifier: Intended Audience :: Developers
Classifier: Intended Audience :: System Administrators
Classifier: Operating System :: OS Independent
Classifier: Environment :: Console
Requires-Python: >=3.7
Requires-Dist: astroid>=2.5.0
Requires-Dist: packaging>=20.0
Requires-Dist: requests>=2.25.0
Requires-Dist: colorama>=0.4.4
Requires-Dist: tomli>=2.0.0; python_version < "3.11"
Requires-Dist: tqdm>=4.50.0
Dynamic: author
Dynamic: requires-python
